README.md
setup.cfg
setup.py
plover_speaker_id/__init__.py
plover_speaker_id/lookup.py
plover_speaker_id/manage.py
plover_speaker_id/utils.py
plover_speaker_id.egg-info/PKG-INFO
plover_speaker_id.egg-info/SOURCES.txt
plover_speaker_id.egg-info/dependency_links.txt
plover_speaker_id.egg-info/entry_points.txt
plover_speaker_id.egg-info/requires.txt
plover_speaker_id.egg-info/top_level.txt
plover_speaker_id.egg-info/zip-safe