Metadata-Version: 2.1
Name: plover-speaker-id
Version: 1.0.0
Summary: Plover plugin for Q&A, speaker designations, and bylines
Home-page: https://github.com/sammdot/plover-speaker-id
License: UNKNOWN
Keywords: plover plover_plugin
Platform: UNKNOWN
Classifier: Programming Language :: Python :: 3.6
Classifier: Programming Language :: Python :: 3.7
Classifier: Programming Language :: Python :: 3.8
Classifier: Programming Language :: Python :: 3.9
